ssh2/__init__.py
ssh2/__main__.py
ssh2/cli/__init__.py
ssh2/cli/main.py
ssh2/cli/parser.py
ssh2/conf.py
ssh2/constants.py
ssh2/exceptions.py
ssh2/models/__init__.py
ssh2/models/auth_method.py
ssh2/models/base.py
ssh2/models/client_config.py
ssh2/models/server_config.py
ssh2/models/session.py
ssh2/plugins/__init__.py
ssh2/plugins/expect.py
ssh2/plugins/ssh.py
ssh2/utils/__init__.py
ssh2/utils/crypto.py
ssh2/utils/tempfile.py
ssh2_wrapper.sh
ssh_mgr-1.1.1.dist-info/entry_points.txt
ssh_mgr-1.1.1.dist-info/METADATA
ssh_mgr-1.1.1.dist-info/WHEEL
ssh_mgr-1.1.1.dist-info/RECORD
