Metadata-Version: 2.1
Name: ssh-mgr
Version: 1.1.1
Summary: A Tool to manage ssh connection
License: MIT
Keywords: ssh
Author: shabbywu
Author-email: shabbywu@qq.com
Requires-Python: >=3.8,<4.0
Classifier: License :: OSI Approved :: MIT License
Classifier: Programming Language :: Python :: 3
Classifier: Programming Language :: Python :: 3.8
Classifier: Programming Language :: Python :: 3.9
Classifier: Programming Language :: Python :: 3.10
Classifier: Programming Language :: Python :: 3.11
Classifier: Programming Language :: Python :: 3.12
Provides-Extra: ioa
Requires-Dist: PyYaml (==6.0.2)
Requires-Dist: aenum (<3)
Requires-Dist: click (>=7.0)
Requires-Dist: cryptography
Requires-Dist: six
Requires-Dist: sqlalchemy (<2)
